llm_forwarder/__init__.py
llm_forwarder/config.py
llm_forwarder/server.py
llm_forwarder-0.1.0.dist-info/METADATA
llm_forwarder-0.1.0.dist-info/WHEEL
llm_forwarder-0.1.0.dist-info/top_level.txt
llm_forwarder-0.1.0.dist-info/RECORD
