Metadata-Version: 2.1
Name: llm-forwarder
Version: 0.1.0
Summary: A configurable forwarder for OpenAI-compatible LLM requests
Home-page: https://github.com/csabakecskemeti/llm_forwarder
Author: Csaba Kecskemeti
Classifier: Programming Language :: Python :: 3
Classifier: Operating System :: OS Independent
Requires-Python: >=3.7
Requires-Dist: Flask>=2.0
Requires-Dist: openai
